spatialmht/__init__.py
spatialmht/analysis.py
spatialmht/detectors.py
spatialmht/field_handling.py
spatialmht/lfdr_estimation.py
spatialmht/load_and_save.py
spatialmht/smom_functions.py
spatialmht/tuda_colors.py
spatialmht/utils.py
spatialmht-2.1.1.dist-info/METADATA
spatialmht-2.1.1.dist-info/WHEEL
spatialmht-2.1.1.dist-info/licenses/LICENSE
spatialmht-2.1.1.dist-info/RECORD
