Metadata-Version: 2.3
Name: spatialmht
Version: 2.1.1
Summary: Code for Spatial Multiple Hypothesis Testing via Local False Discovery Rates with the Spectral Method of Moments
Project-URL: Homepage, https://github.com/mgoelz95/lfdr-sMoM
Project-URL: Bug Tracker, https://github.com/mgoelz95/lfdr-sMoM/issues
Author-email: Martin Goelz <mgoelz@spg.tu-darmstadt.de>
License-File: LICENSE
Classifier: License :: OSI Approved :: MIT License
Classifier: Operating System :: OS Independent
Classifier: Programming Language :: Python :: 3
Requires-Python: >=3.7
